{
  "name": "Example Questionnaire Copy",
  "questions": [
    {
      "id": "name",
      "text": "What is your friend's name?",
      "type": "text"
    },
    {
      "id": "quest",
      "text": "What is your friend's quest?",
      "type": "text"
    },
    {
      "id": "col",
      "text": "What is your friend's favourite colour?",
      "type": "text"
    },
    {
      "id": "velo",
      "text": "What is the air-speed velocity of a quokka?",
      "type": "number"
    },
    {
      "id": "lord",
      "text": "Which is the best lord?",
      "type": "single-select",
      "options": [
        "Lorde",
        "Lord Farquaad"
      ]
    },
    {
      "id": "langs",
      "text": "Which human languages have you used?",
      "type": "multi-select",
      "options": ["English", "Spanish", "Polish", "Japanese", "Korean", "Czech"]
    }
  ]
}
